ffmpeg_debug_qp_parser/__init__.py
ffmpeg_debug_qp_parser/__main__.py
ffmpeg_debug_qp_parser/parse_qp_output.py
ffmpeg_debug_qp_parser-0.1.4.dist-info/LICENSE
ffmpeg_debug_qp_parser-0.1.4.dist-info/METADATA
ffmpeg_debug_qp_parser-0.1.4.dist-info/WHEEL
ffmpeg_debug_qp_parser-0.1.4.dist-info/entry_points.txt
ffmpeg_debug_qp_parser-0.1.4.dist-info/top_level.txt
ffmpeg_debug_qp_parser-0.1.4.dist-info/RECORD
