Metadata-Version: 2.1
Name: ffmpeg_debug_qp_parser
Version: 0.1.4
Summary: Extract QP values of input video
Home-page: https://github.com/slhck/ffmpeg-debug-qp
Author: Werner Robitza
Author-email: werner.robitza@gmail.com
License: MIT
Classifier: Development Status :: 4 - Beta
Classifier: Intended Audience :: Developers
Classifier: Topic :: Multimedia :: Video
Classifier: License :: OSI Approved :: MIT License
Classifier: Programming Language :: Python :: 3
Classifier: Programming Language :: Python :: 3.8
Classifier: Programming Language :: Python :: 3.9
Classifier: Programming Language :: Python :: 3.10
Classifier: Programming Language :: Python :: 3.11
Requires-Python: >=3.8
License-File: LICENSE
